README.md
setup.py
mpi_channels/__init__.py
mpi_channels/frame_buffer.py
mpi_channels/remote_channel.py
mpi_channels/schedule.py
mpi_channels.egg-info/PKG-INFO
mpi_channels.egg-info/SOURCES.txt
mpi_channels.egg-info/dependency_links.txt
mpi_channels.egg-info/top_level.txt