Metadata-Version: 2.1
Name: mpi-channels
Version: 0.1.4
Summary: A RemoteChannel implementation built on top of MPI RMA
Home-page: https://github.com/JBlaschke/mpi-channels
Author: Johannes Blaschke
Author-email: johannes@blaschke.science
License: UNKNOWN
Platform: UNKNOWN
Classifier: Programming Language :: Python :: 3
Classifier: License :: OSI Approved :: MIT License
Classifier: Operating System :: OS Independent
Requires-Python: >=3.8
